[
  {
    "slide": 1,
    "duration": 18.288
  },
  {
    "slide": 2,
    "duration": 10.632
  },
  {
    "slide": 3,
    "duration": 28.368
  },
  {
    "slide": 4,
    "duration": 24.792
  },
  {
    "slide": 5,
    "duration": 16.296
  },
  {
    "slide": 6,
    "duration": 22.104
  },
  {
    "slide": 7,
    "duration": 20.376
  },
  {
    "slide": 8,
    "duration": 22.44
  },
  {
    "slide": 9,
    "duration": 20.736
  },
  {
    "slide": 10,
    "duration": 18.024
  },
  {
    "slide": 11,
    "duration": 17.568
  },
  {
    "slide": 12,
    "duration": 9.072
  }
]
